calculations.py
gpscalculator.py
gait_profile_score-1.0.2.dist-info/LICENSE
gait_profile_score-1.0.2.dist-info/METADATA
gait_profile_score-1.0.2.dist-info/WHEEL
gait_profile_score-1.0.2.dist-info/top_level.txt
gait_profile_score-1.0.2.dist-info/RECORD
