Metadata-Version: 2.1
Name: gait-profile-score
Version: 1.0.2
Summary: Calculates Gait Profile Score
Home-page: UNKNOWN
Author: Michael Jeffryes
Author-email: mike.jeffryes@hotmail.com
License: UNKNOWN
Platform: UNKNOWN
Classifier: Operating System :: OS Independent
Classifier: Programming Language :: Python :: 3
